sunny_order_splitter/__init__.py
sunny_order_splitter/binance_spot.py
sunny_order_splitter/binance_umfutures.py
sunny_order_splitter/core.py
sunny_order_splitter-0.2.3.dist-info/METADATA
sunny_order_splitter-0.2.3.dist-info/WHEEL
sunny_order_splitter-0.2.3.dist-info/top_level.txt
sunny_order_splitter-0.2.3.dist-info/RECORD
