Metadata-Version: 2.1
Name: sunny_order_splitter
Version: 0.2.3
Home-page: https://github.com/sunnytrade/sunny-order-splitter-python-sdk
Author: glede
Author-email: 
Classifier: Programming Language :: Python :: 3
Classifier: License :: OSI Approved :: MIT License
Classifier: Operating System :: OS Independent
Requires-Python: >=3.6
Requires-Dist: binance-connector
Requires-Dist: binance-futures-connector
